.gitignore
Makefile
README.md
VERSION
setup.cfg
setup.py
tpl_README.md
twine_token.sh
web-minify.py
./VERSION
.gitlab/ci.yaml
code_quality/.flake8
code_quality/Makefile
code_quality/mypy.ini
code_quality/pylintrc
design/logo-1024.png
design/logo-1024.svg
requirements/requirements.in
requirements/requirements.txt
requirements/test_requirements.in
requirements/test_requirements.txt
tests/Makefile
tests/__init__.py
tests/pytest.ini
tests/integration/__init__.py
tests/integration/test_true.py
tests/load/__init__.py
tests/load/test_true.py
tests/regressions/test_regressions.py
tests/regressions/expected/beautify/html/basic.html
tests/regressions/expected/beautify/js/arrays.js
tests/regressions/expected/beautify/js/numbers.js
tests/regressions/expected/beautify/js/object_methods.js
tests/regressions/expected/beautify/js/object_properties.js
tests/regressions/expected/beautify/js/objects.js
tests/regressions/expected/beautify/js/statements.js
tests/regressions/expected/beautify/js/strings.js
tests/regressions/input/html/basic.html
tests/regressions/input/js/arrays.js
tests/regressions/input/js/numbers.js
tests/regressions/input/js/object_methods.js
tests/regressions/input/js/object_properties.js
tests/regressions/input/js/objects.js
tests/regressions/input/js/statements.js
tests/regressions/input/js/strings.js
tests/unit/__init__.py
tests/unit/parser_test.html
tests/unit/parser_test2.html
tests/unit/test_true.py
web_minify/__init__.py
web_minify/args.py
web_minify/files.py
web_minify/log.py
web_minify/logo.py
web_minify/minify.py
web_minify/modes.py
web_minify/processor.py
web_minify/time.py
web_minify.egg-info/PKG-INFO
web_minify.egg-info/SOURCES.txt
web_minify.egg-info/dependency_links.txt
web_minify.egg-info/entry_points.txt
web_minify.egg-info/requires.txt
web_minify.egg-info/top_level.txt
web_minify.egg-info/zip-safe
web_minify/handlers/__init__.py
web_minify/handlers/jinja.py
web_minify/handlers/jpeg.py
web_minify/handlers/json.py
web_minify/handlers/png.py
web_minify/handlers/sass.py
web_minify/handlers/sql.py
web_minify/handlers/css/__init__.py
web_minify/handlers/css/css.py
web_minify/handlers/css/variables.py
web_minify/handlers/html/__init__.py
web_minify/handlers/html/beautify.py
