Metadata-Version: 2.1
Name: web-minify
Version: 1.1.3
Summary: CSS HTML JS SVG PNG JPEG Minifier
Home-page: https://gitlab.com/octomy/web-minifier
Author: Lennart Rolland
Author-email: lennart@octomy.org
Maintainer: Lennart Rolland
Maintainer-email: lennart@octomy.org
License: GPL-3 LGPL-3 MIT
Download-URL: https://gitlab.com/octomy/web-minify
Project-URL: Docs, https://gitlab.com/octomy/web-minify/README.md
Project-URL: Bugs, https://gitlab.com/octomy/web-minify/-/issues
Project-URL: C.I., https://gitlab.com/octomy/web-minify/pipelines
Keywords: python3,CSS,HTML,JS,SVG,PNG,JPEG,Compressor,CSS3,HTML5,Web,Javascript,Minifier,Minify,Uglify,Obfuscator
Platform: Linux
Classifier: Development Status :: 3 - Alpha
Classifier: Intended Audience :: Developers
Classifier: Intended Audience :: Other Audience
Classifier: Topic :: Utilities
Classifier: Natural Language :: English
Classifier: Operating System :: POSIX :: Linux
Classifier: Programming Language :: Python :: 3.7
Classifier: Topic :: Other/Nonlisted Topic
Requires-Python: >=3.7.4
